<?xml version="1.0" encoding="utf-8"?>
<TextureAtlas imagePath="NOTE_assets-chip.png">
	<!-- Created with Adobe Animate version 24.0.1.329 -->
	<!-- http://www.adobe.com/products/animate.html -->
	<SubTexture name="arrowDOWN0000" x="396" y="0" width="157" height="157"/>
	<SubTexture name="arrowLEFT0000" x="396" y="0" width="157" height="157"/>
	<SubTexture name="arrowRIGHT0000" x="396" y="0" width="157" height="157"/>
	<SubTexture name="arrowUP0000" x="396" y="0" width="157" height="157"/>
	<SubTexture name="blue0000" x="0" y="0" width="157" height="157"/>
	<SubTexture name="blue hold end0000" x="161" y="0" width="113" height="50"/>
	<SubTexture name="blue hold piece0000" x="278" y="0" width="114" height="76"/>
	<SubTexture name="down confirm0000" x="557" y="0" width="256" height="256"/>
	<SubTexture name="down confirm0001" x="0" y="260" width="256" height="256"/>
	<SubTexture name="down confirm0002" x="260" y="260" width="256" height="256"/>
	<SubTexture name="down confirm0003" x="260" y="260" width="256" height="256"/>
	<SubTexture name="down press0000" x="520" y="260" width="157" height="157"/>
	<SubTexture name="down press0001" x="520" y="260" width="157" height="157"/>
	<SubTexture name="down press0002" x="681" y="260" width="157" height="157"/>
	<SubTexture name="down press0003" x="681" y="260" width="157" height="157"/>
	<SubTexture name="green0000" x="0" y="0" width="157" height="157"/>
	<SubTexture name="green hold end0000" x="161" y="0" width="113" height="50"/>
	<SubTexture name="green hold piece0000" x="278" y="0" width="114" height="76"/>
	<SubTexture name="left confirm0000" x="557" y="0" width="256" height="256"/>
	<SubTexture name="left confirm0001" x="0" y="260" width="256" height="256"/>
	<SubTexture name="left confirm0002" x="0" y="520" width="256" height="256"/>
	<SubTexture name="left confirm0003" x="0" y="520" width="256" height="256"/>
	<SubTexture name="left press0000" x="520" y="260" width="157" height="157"/>
	<SubTexture name="left press0001" x="520" y="260" width="157" height="157"/>
	<SubTexture name="left press0002" x="681" y="260" width="157" height="157"/>
	<SubTexture name="left press0003" x="681" y="260" width="157" height="157"/>
	<SubTexture name="purple0000" x="0" y="0" width="157" height="157"/>
	<SubTexture name="purple hold end0000" x="161" y="0" width="113" height="50"/>
	<SubTexture name="purple hold piece0000" x="278" y="0" width="114" height="76"/>
	<SubTexture name="red0000" x="0" y="0" width="157" height="157"/>
	<SubTexture name="red hold end0000" x="161" y="0" width="113" height="50"/>
	<SubTexture name="red hold piece0000" x="278" y="0" width="114" height="76"/>
	<SubTexture name="right confirm0000" x="557" y="0" width="256" height="256"/>
	<SubTexture name="right confirm0001" x="0" y="260" width="256" height="256"/>
	<SubTexture name="right confirm0002" x="260" y="520" width="256" height="256"/>
	<SubTexture name="right confirm0003" x="260" y="520" width="256" height="256"/>
	<SubTexture name="right press0000" x="520" y="260" width="157" height="157"/>
	<SubTexture name="right press0001" x="520" y="260" width="157" height="157"/>
	<SubTexture name="right press0002" x="681" y="260" width="157" height="157"/>
	<SubTexture name="right press0003" x="681" y="260" width="157" height="157"/>
	<SubTexture name="up confirm0000" x="557" y="0" width="256" height="256"/>
	<SubTexture name="up confirm0001" x="0" y="260" width="256" height="256"/>
	<SubTexture name="up confirm0002" x="520" y="520" width="256" height="256"/>
	<SubTexture name="up confirm0003" x="520" y="520" width="256" height="256"/>
	<SubTexture name="up press0000" x="520" y="260" width="157" height="157"/>
	<SubTexture name="up press0001" x="520" y="260" width="157" height="157"/>
	<SubTexture name="up press0002" x="681" y="260" width="157" height="157"/>
	<SubTexture name="up press0003" x="681" y="260" width="157" height="157"/>
</TextureAtlas>
