{
	"dialogue": [
		{
			"expression": "talk",
			"text": "Yoo bestfriend wsup < 3",
			"boxState": "normal",
			"sound": "",
			"speed": 0.05,
			"portrait": "carol"
		},
		{
			"expression": "excited",
			"text": "Hey, girly this my bf",
			"boxState": "normal",
			"sound": "",
			"speed": 0.05,
			"portrait": "gf"
		},
		{
			"expression": "talk",
			"text": "He mad short ngl. ",
			"boxState": "normal",
			"sound": "",
			"speed": 0.05,
			"portrait": "carol"
		},
		{
			"expression": "talk",
			"text": "Ayo peep this bop i whipped up",
			"boxState": "normal",
			"sound": "",
			"speed": 0.05,
			"portrait": "carol"
		},
		{
			"expression": "confused",
			"text": "Do it bang tho?",
			"boxState": "normal",
			"sound": "",
			"speed": 0.05,
			"portrait": "gf"
		},
		{
			"expression": "excited",
			"text": "beep opboobi",
			"boxState": "normal",
			"sound": "",
			"speed": 0.05,
			"portrait": "bf"
		},
		{
			"expression": "talk",
			"text": "What?",
			"boxState": "normal",
			"sound": "",
			"speed": 0.05,
			"portrait": "carol"
		}
	]
}